[
  {
    "per_page": 3,
    "total_entries": 8,
    "total_pages": 4,
    "page": 1
  },
  [
    {
      "id": 1,
      "vaccinated": true,
      "price": 100,
      "name": "Lisa",
      "breed": "Angora",
      "gender": 0,
      "birthday": 1273708800,
      "description": "Very good and smart cat.",
      "photos": [
        "js/assets/images/cats/lisa_800x600.png"
      ]
    },
    {
      "id": 2,
      "vaccinated": true,
      "price": 200,
      "name": "Bart",
      "breed": "Mixed-breed",
      "gender": 1,
      "birthday": 1273708800,
      "description": "Very good and mischievous cat.",
      "photos": [
        "js/assets/images/cats/bart_800x600.png"
      ]
    },
    {
      "id": 3,
      "vaccinated": true,
      "price": 150,
      "name": "Homer",
      "breed": "Mixed-breed",
      "gender": 1,
      "birthday": 1455235200,
      "description": "Very good and lazy cat.",
      "photos": [
        "js/assets/images/cats/homer_800x600.png"
      ]
    },
    {
      "id": 4,
      "vaccinated": true,
      "price": 130,
      "name": "Marge",
      "breed": "Mixed-breed",
      "gender": 0,
      "birthday": 1423699200,
      "description": "Very good and patient cat.",
      "photos": [
        "js/assets/images/cats/marge_800x600.png"
      ]
    },
    {
      "id": 5,
      "vaccinated": true,
      "price": 210,
      "name": "Maggie",
      "breed": "Russian blue",
      "gender": 0,
      "birthday": 1399939200,
      "description": "Very good and silent cat.",
      "photos": [
        "js/assets/images/cats/maggie_800x600.png"
      ]
    },
    {
      "id": 6,
      "vaccinated": false,
      "price": 180,
      "name": "Todd",
      "breed": "Scottish Fold",
      "gender": 1,
      "birthday": 1399939200,
      "description": "Very good and accurate cat.",
      "photos": [
        "js/assets/images/cats/todd_800x600.png"
      ]
    },
    {
      "id": 7,
      "price": 180,
      "vaccinated": true,
      "name": "Moe",
      "breed": "Siamese",
      "gender": 1,
      "birthday": 1336867200,
      "photos": [
        "js/assets/images/cats/moe_800x600.png"
      ]
    },
    {
      "id": 8,
      "vaccinated": true,
      "price": 180,
      "name": " Krusty",
      "breed": "Turkish Van",
      "gender": 1,
      "birthday": 1305244800,
      "description": "Very good and gay cat.",
      "photos": [
        "js/assets/images/cats/krusty_800x600.png"
      ]
    }
  ]
]
